setup.py
combined_clustering_algorithm/__init__.py
combined_clustering_algorithm/canopy.py
combined_clustering_algorithm/k_means.py
combined_clustering_algorithm/visualization.py
combined_clustering_algorithm.egg-info/PKG-INFO
combined_clustering_algorithm.egg-info/SOURCES.txt
combined_clustering_algorithm.egg-info/dependency_links.txt
combined_clustering_algorithm.egg-info/top_level.txt